{
  "meta": {
    "id": "2-3-n008",
    "typ": "nakresli",
    "nazev": "Nakresli písmeno N",
    "tematicky_okruh": "2.3-pismena",
    "difficulty": 2,
    "koncepty": [
      "forward",
      "backward",
      "right",
      "left",
      "pen_up",
      "pen_down"
    ],
    "verze": 2,
    "stav": "draft",
    "poznamky": "N (zjednodušené) = levá svislice 80px dolů, PenUp zpět nahoru, left(90), PenDown, horní příčka 80px vpravo, right(90), pravá svislice 80px dolů. Tvar ⊓. Start: (125,75) směr dolů (270°)."
  },
  "cms": {
    "task_text": "Naprogramujte želvu, aby nakreslila [hlp]zjednodušené písmeno N[/hlp] — dvě svislé části jsou 80 px, horní příčka je také 80 px.",
    "pozice_podkladu": {
      "x": 125,
      "y": 75,
      "uhel": 270
    },
    "pozice_kurzoru": {
      "x": 125,
      "y": 75,
      "uhel": 270
    },
    "sketch_code": "turtle.setPenWidth(5);turtle.forward(80);turtle.PenUp();turtle.backward(80);turtle.left(90);turtle.PenDown();turtle.forward(80);turtle.right(90);turtle.forward(80);",
    "toolbox_json": {
      "kind": "flyoutToolbox",
      "contents": [
        {
          "kind": "block",
          "type": "turtle_forward",
          "fields": {
            "DISTANCE": 80
          }
        },
        {
          "kind": "block",
          "type": "turtle_backward",
          "fields": {
            "DISTANCE": 80
          }
        },
        {
          "kind": "block",
          "type": "turtle_right",
          "fields": {
            "ANGLE": 90
          }
        },
        {
          "kind": "block",
          "type": "turtle_left",
          "fields": {
            "ANGLE": 90
          }
        },
        {
          "kind": "block",
          "type": "turtle_pen_up"
        },
        {
          "kind": "block",
          "type": "turtle_pen_down"
        }
      ]
    },
    "start_blocks_xml": "",
    "validace": {
      "cary_delky": "80,80,80",
      "cary_tolerance": 5,
      "uhly": "90,-90",
      "uhly_tolerance": 10,
      "max_bloku": 8,
      "typy_bloku": "turtle_forward,turtle_backward,turtle_right,turtle_left,turtle_pen_up,turtle_pen_down"
    },
    "spravna_odpoved_xml": "<xml xmlns=\"https://developers.google.com/blockly/xml\"><block type=\"turtle_forward\" x=\"50\" y=\"50\"><field name=\"DISTANCE\">80</field><next><block type=\"turtle_pen_up\"><next><block type=\"turtle_backward\"><field name=\"DISTANCE\">80</field><next><block type=\"turtle_left\"><field name=\"ANGLE\">90</field><next><block type=\"turtle_pen_down\"><next><block type=\"turtle_forward\"><field name=\"DISTANCE\">80</field><next><block type=\"turtle_right\"><field name=\"ANGLE\">90</field><next><block type=\"turtle_forward\"><field name=\"DISTANCE\">80</field></block></next></block></next></block></next></block></next></block></next></block></next></block></next></block></xml>"
  }
}